PyDI/__init__.py
PyDI/datatranslation/__init__.py
PyDI/datatranslation/base.py
PyDI/datatranslation/mapping_translator.py
PyDI/entitymatching/__init__.py
PyDI/entitymatching/base.py
PyDI/entitymatching/comparators.py
PyDI/entitymatching/evaluation.py
PyDI/entitymatching/feature_extraction.py
PyDI/entitymatching/llm_based.py
PyDI/entitymatching/ml_based.py
PyDI/entitymatching/plm_based.py
PyDI/entitymatching/rule_based.py
PyDI/entitymatching/text_formatting.py
PyDI/entitymatching/blocking/__init__.py
PyDI/entitymatching/blocking/base.py
PyDI/entitymatching/blocking/embedding.py
PyDI/entitymatching/blocking/noblocking.py
PyDI/entitymatching/blocking/sorted_neighbourhood.py
PyDI/entitymatching/blocking/standard.py
PyDI/entitymatching/blocking/token_blocking.py
PyDI/entitymatching/labeling_tool/interactive.py
PyDI/entitymatching/labeling_tool/streamlit_app.py
PyDI/entitymatching/post_clustering/__init__.py
PyDI/entitymatching/post_clustering/base.py
PyDI/entitymatching/post_clustering/centre_clusterer.py
PyDI/entitymatching/post_clustering/connected_components.py
PyDI/entitymatching/post_clustering/greedy_one_to_one.py
PyDI/entitymatching/post_clustering/hierarchical_clusterer.py
PyDI/entitymatching/post_clustering/maximum_bipartite_matching.py
PyDI/entitymatching/post_clustering/stable_matching.py
PyDI/fusion/__init__.py
PyDI/fusion/analysis.py
PyDI/fusion/base.py
PyDI/fusion/engine.py
PyDI/fusion/evaluation.py
PyDI/fusion/provenance.py
PyDI/fusion/reporting.py
PyDI/fusion/strategy.py
PyDI/fusion/conflict_resolution/__init__.py
PyDI/fusion/conflict_resolution/date.py
PyDI/fusion/conflict_resolution/general.py
PyDI/fusion/conflict_resolution/list.py
PyDI/fusion/conflict_resolution/numeric.py
PyDI/fusion/conflict_resolution/string.py
PyDI/fusion/conflict_resolution/utils.py
PyDI/informationextraction/__init__.py
PyDI/informationextraction/autorules.py
PyDI/informationextraction/base.py
PyDI/informationextraction/code.py
PyDI/informationextraction/evaluation.py
uma_pydi-0.1.5.dist-info/licenses/LICENSE
uma_pydi-0.1.5.dist-info/METADATA
uma_pydi-0.1.5.dist-info/WHEEL
uma_pydi-0.1.5.dist-info/top_level.txt
uma_pydi-0.1.5.dist-info/RECORD
