Metadata-Version: 2.4
Name: uma-pydi
Version: 0.1.5
Summary: PyDI - Python Data Integration Framework
Home-page: https://github.com/wbsg-uni-mannheim/PyDI/
Author: Ralph Peeters, Aaron Steiner, Christian Bizer
Author-email: Ralph Peeters <ralph.peeters@gmx.de>, Aaron Steiner <aaron.steiner@uni-mannheim.de>, Christian Bizer <christian.bizer@uni-mannheim.de>
License:                                  Apache License
Project-URL: Homepage, https://github.com/wbsg-uni-mannheim/PyDI/
Project-URL: Repository, https://github.com/wbsg-uni-mannheim/PyDI/
Keywords: data-integration,entity-matching,schema-matching,data-fusion,data-translation,information-extraction
Classifier: Development Status :: 3 - Alpha
Classifier: Intended Audience :: Developers
Classifier: Intended Audience :: Science/Research
Classifier: License :: OSI Approved :: Apache Software License
Classifier: Programming Language :: Python :: 3
Classifier: Programming Language :: Python :: 3.12
Classifier: Topic :: Scientific/Engineering :: Information Analysis
Classifier: Topic :: Software Development :: Libraries :: Python Modules
Requires-Python: >=3.12
License-File: LICENSE
Requires-Dist: pandas<3.0.0,>=2.0.0
Requires-Dist: numpy<2.2.0,>=2.1.0
Requires-Dist: scikit-learn<2.0.0,>=1.3.0
Requires-Dist: networkx<4.0,>=3.0
Requires-Dist: rapidfuzz<4.0.0,>=3.0.0
Requires-Dist: textdistance[extras]<5.0.0,>=4.5.0
Requires-Dist: sentence-transformers<6.0.0,>=5.0.0
Requires-Dist: pydantic<3.0.0,>=2.0.0
Requires-Dist: ydata-profiling<5.0.0,>=4.0.0
Requires-Dist: sweetviz<3.0.0,>=2.3.0
Requires-Dist: transformers<5.0.0,>=4.30.0
Requires-Dist: lxml<6.0.0,>=4.9.0
Requires-Dist: Babel<3.0,>=2.12
Requires-Dist: langchain-core<0.4.0,>=0.1.0
Requires-Dist: langchain-openai<0.4.0,>=0.3.0
Requires-Dist: python-dotenv<1.1.0,>=1.0.0
Requires-Dist: tabulate<1.0.0,>=0.9.0
Provides-Extra: dev
Requires-Dist: pytest<8.0,>=7.0; extra == "dev"
Requires-Dist: pytest-cov<5.0.0,>=4.0.0; extra == "dev"
Requires-Dist: black<24.0,>=23.0; extra == "dev"
Requires-Dist: isort<6.0.0,>=5.12.0; extra == "dev"
Requires-Dist: flake8<7.0.0,>=6.0.0; extra == "dev"
Requires-Dist: mypy<2.0.0,>=1.5.0; extra == "dev"
Requires-Dist: pre-commit<4.0.0,>=3.0.0; extra == "dev"
Requires-Dist: twine; extra == "dev"
Provides-Extra: docs
Requires-Dist: sphinx<8.0.0,>=7.0.0; extra == "docs"
Requires-Dist: sphinx-rtd-theme<2.0.0,>=1.3.0; extra == "docs"
Requires-Dist: myst-parser<3.0.0,>=2.0.0; extra == "docs"
Provides-Extra: ui
Requires-Dist: streamlit<2.0.0,>=1.32.0; extra == "ui"
Provides-Extra: test
Requires-Dist: pytest<8.0,>=7.0; extra == "test"
Requires-Dist: pytest-cov<5.0.0,>=4.0.0; extra == "test"
Requires-Dist: pytest-mock<4.0.0,>=3.11.0; extra == "test"
Provides-Extra: llm
Requires-Dist: langchain-openai<0.4.0,>=0.3.0; extra == "llm"
Provides-Extra: embedding
Requires-Dist: sentence-transformers<6.0.0,>=5.0.0; extra == "embedding"
Requires-Dist: torch<3.0.0,>=2.0.0; extra == "embedding"
Provides-Extra: plm
Requires-Dist: transformers<5.0.0,>=4.30.0; extra == "plm"
Requires-Dist: torch<3.0.0,>=2.0.0; extra == "plm"
Requires-Dist: sentence-transformers<6.0.0,>=5.0.0; extra == "plm"
Provides-Extra: faiss
Requires-Dist: faiss-cpu<2.0.0,>=1.7.4; extra == "faiss"
Provides-Extra: hnsw
Requires-Dist: hnswlib<1.0.0,>=0.8.0; extra == "hnsw"
Dynamic: author
Dynamic: home-page
Dynamic: license-file
Dynamic: requires-python
